{"nodes": [{"id": "c_users_even_documents_all_in_one_src_modules_ai_gn_agent_runtime_codex_codexruntime_ts", "label": "CodexRuntime.ts", "file_type": "code", "source_file": "C:\\Users\\Even\\Documents\\ALL-IN-ONE\\src\\modules\\ai\\gn-agent\\runtime\\codex\\CodexRuntime.ts", "source_location": "L1"}, {"id": "codex_codexruntime_codexruntime", "label": "CodexRuntime", "file_type": "code", "source_file": "C:\\Users\\Even\\Documents\\ALL-IN-ONE\\src\\modules\\ai\\gn-agent\\runtime\\codex\\CodexRuntime.ts", "source_location": "L7"}, {"id": "codex_codexruntime_codexruntime_getmatchingconfigs", "label": ".getMatchingConfigs()", "file_type": "code", "source_file": "C:\\Users\\Even\\Documents\\ALL-IN-ONE\\src\\modules\\ai\\gn-agent\\runtime\\codex\\CodexRuntime.ts", "source_location": "L10"}, {"id": "codex_codexruntime_codexruntime_resolvepreferredconfig", "label": ".resolvePreferredConfig()", "file_type": "code", "source_file": "C:\\Users\\Even\\Documents\\ALL-IN-ONE\\src\\modules\\ai\\gn-agent\\runtime\\codex\\CodexRuntime.ts", "source_location": "L14"}, {"id": "codex_codexruntime_codexruntime_executeprompt", "label": ".executePrompt()", "file_type": "code", "source_file": "C:\\Users\\Even\\Documents\\ALL-IN-ONE\\src\\modules\\ai\\gn-agent\\runtime\\codex\\CodexRuntime.ts", "source_location": "L21"}, {"id": "codex_codexruntime_codexruntime_getstatus", "label": ".getStatus()", "file_type": "code", "source_file": "C:\\Users\\Even\\Documents\\ALL-IN-ONE\\src\\modules\\ai\\gn-agent\\runtime\\codex\\CodexRuntime.ts", "source_location": "L50"}], "edges": [{"source": "c_users_even_documents_all_in_one_src_modules_ai_gn_agent_runtime_codex_codexruntime_ts", "target": "c_users_even_documents_all_in_one_src_modules_ai_core_aiservice_ts", "relation": "imports_from", "context": "import", "confidence": "EXTRACTED", "source_file": "C:\\Users\\Even\\Documents\\ALL-IN-ONE\\src\\modules\\ai\\gn-agent\\runtime\\codex\\CodexRuntime.ts", "source_location": "L1", "weight": 1.0}, {"source": "c_users_even_documents_all_in_one_src_modules_ai_gn_agent_runtime_codex_codexruntime_ts", "target": "core_aiservice_aiservice", "relation": "imports", "context": "import", "confidence": "EXTRACTED", "source_file": "C:\\Users\\Even\\Documents\\ALL-IN-ONE\\src\\modules\\ai\\gn-agent\\runtime\\codex\\CodexRuntime.ts", "source_location": "L1", "weight": 1.0}, {"source": "c_users_even_documents_all_in_one_src_modules_ai_gn_agent_runtime_codex_codexruntime_ts", "target": "c_users_even_documents_all_in_one_src_modules_ai_core_aiservice_ts", "relation": "imports_from", "context": "import", "confidence": "EXTRACTED", "source_file": "C:\\Users\\Even\\Documents\\ALL-IN-ONE\\src\\modules\\ai\\gn-agent\\runtime\\codex\\CodexRuntime.ts", "source_location": "L2", "weight": 1.0}, {"source": "c_users_even_documents_all_in_one_src_modules_ai_gn_agent_runtime_codex_codexruntime_ts", "target": "core_aiservice_aitextstreamevent", "relation": "imports", "context": "import", "confidence": "EXTRACTED", "source_file": "C:\\Users\\Even\\Documents\\ALL-IN-ONE\\src\\modules\\ai\\gn-agent\\runtime\\codex\\CodexRuntime.ts", "source_location": "L2", "weight": 1.0}, {"source": "c_users_even_documents_all_in_one_src_modules_ai_gn_agent_runtime_codex_codexruntime_ts", "target": "c_users_even_documents_all_in_one_src_modules_ai_store_aiconfigstate_ts", "relation": "imports_from", "context": "import", "confidence": "EXTRACTED", "source_file": "C:\\Users\\Even\\Documents\\ALL-IN-ONE\\src\\modules\\ai\\gn-agent\\runtime\\codex\\CodexRuntime.ts", "source_location": "L3", "weight": 1.0}, {"source": "c_users_even_documents_all_in_one_src_modules_ai_gn_agent_runtime_codex_codexruntime_ts", "target": "store_aiconfigstate_aiconfigentry", "relation": "imports", "context": "import", "confidence": "EXTRACTED", "source_file": "C:\\Users\\Even\\Documents\\ALL-IN-ONE\\src\\modules\\ai\\gn-agent\\runtime\\codex\\CodexRuntime.ts", "source_location": "L3", "weight": 1.0}, {"source": "c_users_even_documents_all_in_one_src_modules_ai_gn_agent_runtime_codex_codexruntime_ts", "target": "c_users_even_documents_all_in_one_src_modules_ai_store_aiconfigstate_ts", "relation": "imports_from", "context": "import", "confidence": "EXTRACTED", "source_file": "C:\\Users\\Even\\Documents\\ALL-IN-ONE\\src\\modules\\ai\\gn-agent\\runtime\\codex\\CodexRuntime.ts", "source_location": "L4", "weight": 1.0}, {"source": "c_users_even_documents_all_in_one_src_modules_ai_gn_agent_runtime_codex_codexruntime_ts", "target": "store_aiconfigstate_toruntimeaiconfig", "relation": "imports", "context": "import", "confidence": "EXTRACTED", "source_file": "C:\\Users\\Even\\Documents\\ALL-IN-ONE\\src\\modules\\ai\\gn-agent\\runtime\\codex\\CodexRuntime.ts", "source_location": "L4", "weight": 1.0}, {"source": "c_users_even_documents_all_in_one_src_modules_ai_gn_agent_runtime_codex_codexruntime_ts", "target": "c_users_even_documents_all_in_one_src_modules_ai_gn_agent_runtime_types_ts", "relation": "imports_from", "context": "import", "confidence": "EXTRACTED", "source_file": "C:\\Users\\Even\\Documents\\ALL-IN-ONE\\src\\modules\\ai\\gn-agent\\runtime\\codex\\CodexRuntime.ts", "source_location": "L5", "weight": 1.0}, {"source": "c_users_even_documents_all_in_one_src_modules_ai_gn_agent_runtime_codex_codexruntime_ts", "target": "runtime_types_gnagentruntimecontext", "relation": "imports", "context": "import", "confidence": "EXTRACTED", "source_file": "C:\\Users\\Even\\Documents\\ALL-IN-ONE\\src\\modules\\ai\\gn-agent\\runtime\\codex\\CodexRuntime.ts", "source_location": "L5", "weight": 1.0}, {"source": "c_users_even_documents_all_in_one_src_modules_ai_gn_agent_runtime_codex_codexruntime_ts", "target": "runtime_types_gnagentruntimestatus", "relation": "imports", "context": "import", "confidence": "EXTRACTED", "source_file": "C:\\Users\\Even\\Documents\\ALL-IN-ONE\\src\\modules\\ai\\gn-agent\\runtime\\codex\\CodexRuntime.ts", "source_location": "L5", "weight": 1.0}, {"source": "c_users_even_documents_all_in_one_src_modules_ai_gn_agent_runtime_codex_codexruntime_ts", "target": "codex_codexruntime_codexruntime", "relation": "contains", "confidence": "EXTRACTED", "source_file": "C:\\Users\\Even\\Documents\\ALL-IN-ONE\\src\\modules\\ai\\gn-agent\\runtime\\codex\\CodexRuntime.ts", "source_location": "L7", "weight": 1.0}, {"source": "codex_codexruntime_codexruntime", "target": "codex_codexruntime_codexruntime_getmatchingconfigs", "relation": "method", "confidence": "EXTRACTED", "source_file": "C:\\Users\\Even\\Documents\\ALL-IN-ONE\\src\\modules\\ai\\gn-agent\\runtime\\codex\\CodexRuntime.ts", "source_location": "L10", "weight": 1.0}, {"source": "codex_codexruntime_codexruntime", "target": "codex_codexruntime_codexruntime_resolvepreferredconfig", "relation": "method", "confidence": "EXTRACTED", "source_file": "C:\\Users\\Even\\Documents\\ALL-IN-ONE\\src\\modules\\ai\\gn-agent\\runtime\\codex\\CodexRuntime.ts", "source_location": "L14", "weight": 1.0}, {"source": "codex_codexruntime_codexruntime", "target": "codex_codexruntime_codexruntime_executeprompt", "relation": "method", "confidence": "EXTRACTED", "source_file": "C:\\Users\\Even\\Documents\\ALL-IN-ONE\\src\\modules\\ai\\gn-agent\\runtime\\codex\\CodexRuntime.ts", "source_location": "L21", "weight": 1.0}, {"source": "codex_codexruntime_codexruntime", "target": "codex_codexruntime_codexruntime_getstatus", "relation": "method", "confidence": "EXTRACTED", "source_file": "C:\\Users\\Even\\Documents\\ALL-IN-ONE\\src\\modules\\ai\\gn-agent\\runtime\\codex\\CodexRuntime.ts", "source_location": "L50", "weight": 1.0}, {"source": "codex_codexruntime_codexruntime_resolvepreferredconfig", "target": "codex_codexruntime_codexruntime_getmatchingconfigs", "relation": "calls", "context": "call", "confidence": "EXTRACTED", "source_file": "C:\\Users\\Even\\Documents\\ALL-IN-ONE\\src\\modules\\ai\\gn-agent\\runtime\\codex\\CodexRuntime.ts", "source_location": "L15", "weight": 1.0}], "raw_calls": [{"caller_nid": "codex_codexruntime_codexruntime_getmatchingconfigs", "callee": "filter", "is_member_call": true, "source_file": "C:\\Users\\Even\\Documents\\ALL-IN-ONE\\src\\modules\\ai\\gn-agent\\runtime\\codex\\CodexRuntime.ts", "source_location": "L11"}, {"caller_nid": "codex_codexruntime_codexruntime_resolvepreferredconfig", "callee": "find", "is_member_call": true, "source_file": "C:\\Users\\Even\\Documents\\ALL-IN-ONE\\src\\modules\\ai\\gn-agent\\runtime\\codex\\CodexRuntime.ts", "source_location": "L15"}, {"caller_nid": "codex_codexruntime_codexruntime_executeprompt", "callee": "getConfig", "is_member_call": true, "source_file": "C:\\Users\\Even\\Documents\\ALL-IN-ONE\\src\\modules\\ai\\gn-agent\\runtime\\codex\\CodexRuntime.ts", "source_location": "L35"}, {"caller_nid": "codex_codexruntime_codexruntime_executeprompt", "callee": "setConfig", "is_member_call": true, "source_file": "C:\\Users\\Even\\Documents\\ALL-IN-ONE\\src\\modules\\ai\\gn-agent\\runtime\\codex\\CodexRuntime.ts", "source_location": "L36"}, {"caller_nid": "codex_codexruntime_codexruntime_executeprompt", "callee": "toRuntimeAIConfig", "is_member_call": false, "source_file": "C:\\Users\\Even\\Documents\\ALL-IN-ONE\\src\\modules\\ai\\gn-agent\\runtime\\codex\\CodexRuntime.ts", "source_location": "L36"}, {"caller_nid": "codex_codexruntime_codexruntime_executeprompt", "callee": "completeText", "is_member_call": true, "source_file": "C:\\Users\\Even\\Documents\\ALL-IN-ONE\\src\\modules\\ai\\gn-agent\\runtime\\codex\\CodexRuntime.ts", "source_location": "L38"}, {"caller_nid": "codex_codexruntime_codexruntime_executeprompt", "callee": "setConfig", "is_member_call": true, "source_file": "C:\\Users\\Even\\Documents\\ALL-IN-ONE\\src\\modules\\ai\\gn-agent\\runtime\\codex\\CodexRuntime.ts", "source_location": "L46"}, {"caller_nid": "codex_codexruntime_codexruntime_getstatus", "callee": "Boolean", "is_member_call": false, "source_file": "C:\\Users\\Even\\Documents\\ALL-IN-ONE\\src\\modules\\ai\\gn-agent\\runtime\\codex\\CodexRuntime.ts", "source_location": "L52"}, {"caller_nid": "codex_codexruntime_codexruntime_getstatus", "callee": "trim", "is_member_call": true, "source_file": "C:\\Users\\Even\\Documents\\ALL-IN-ONE\\src\\modules\\ai\\gn-agent\\runtime\\codex\\CodexRuntime.ts", "source_location": "L56"}, {"caller_nid": "codex_codexruntime_codexruntime_getstatus", "callee": "trim", "is_member_call": true, "source_file": "C:\\Users\\Even\\Documents\\ALL-IN-ONE\\src\\modules\\ai\\gn-agent\\runtime\\codex\\CodexRuntime.ts", "source_location": "L57"}, {"caller_nid": "codex_codexruntime_codexruntime_getstatus", "callee": "Boolean", "is_member_call": false, "source_file": "C:\\Users\\Even\\Documents\\ALL-IN-ONE\\src\\modules\\ai\\gn-agent\\runtime\\codex\\CodexRuntime.ts", "source_location": "L59"}]}